backend/app.py
backend/chromadb_setup.py
backend/config.py
backend/debug_chromadb.py
backend/image_extractor.py
backend/next_steps_graph.py
backend/reset_chromadb.py
backend/test_image.jpg
backend/test_image.py
backend/agents/email_agent.py
backend/chroma_db/chroma.sqlite3
backend/utils/__init__.py
backend/utils/comprehensive_document_processor.py
backend/utils/document_loader.py
backend/utils/file_analyzer.py
backend/utils/response_generator.py
backend/utils/url_scraper.py
backend/utils/vision_processor.py
frontend/package-lock.json
frontend/streamlit_app.py
frontend/user_database.json
frontend/components/auth.py
frontend/components/chat.py
frontend/components/file_analysis.py
frontend/components/sidebar.py
frontend/components/upload.py
frontend/static/scu_logo.png
frontend/utils/api_client.py
frontend/utils/formatters.py
finance_chatbot-1.0.12.dist-info/METADATA
finance_chatbot-1.0.12.dist-info/WHEEL
finance_chatbot-1.0.12.dist-info/top_level.txt
finance_chatbot-1.0.12.dist-info/RECORD
