Metadata-Version: 2.4
Name: finance-chatbot
Version: 1.0.12
Summary: An intelligent document analysis and Q&A system for Santa Clara University Finance Department
Home-page: https://github.com/pradeept3/finance-chatbot
Author: Pradeep Kumar Tripathy
Author-email: Pradeep Kumar Tripathy <tripathy.pradeep@gmail.com>
License: MIT
Project-URL: Homepage, https://github.com/pradeept3/finance-chatbot
Project-URL: Documentation, https://github.com/pradeept3/finance-chatbot/blob/main/README.md
Project-URL: Repository, https://github.com/pradeept3/finance-chatbot.git
Project-URL: Issues, https://github.com/pradeept3/finance-chatbot/issues
Keywords: chatbot,finance,document-analysis,qa-system,streamlit,flask,generative-ai
Classifier: Development Status :: 4 - Beta
Classifier: Environment :: Web Environment
Classifier: Intended Audience :: Education
Classifier: Natural Language :: English
Classifier: Operating System :: OS Independent
Classifier: Programming Language :: Python :: 3
Classifier: Programming Language :: Python :: 3.8
Classifier: Programming Language :: Python :: 3.9
Classifier: Programming Language :: Python :: 3.10
Classifier: Programming Language :: Python :: 3.11
Classifier: Topic :: Education
Classifier: Topic :: Office/Business
Requires-Python: >=3.8
Requires-Dist: streamlit>=1.28.1
Requires-Dist: streamlit-option-menu>=0.3.6
Requires-Dist: Flask>=2.3.0
Requires-Dist: Flask-CORS>=4.0.0
Requires-Dist: python-dotenv>=1.0.0
Requires-Dist: chromadb>=1.3.4
Requires-Dist: sentence-transformers>=2.2.2
Requires-Dist: unstructured[local-inference]>=0.18.20
Requires-Dist: python-docx>=1.2.0
Requires-Dist: pypdf>=6.3.0
Requires-Dist: openpyxl>=3.1.5
Requires-Dist: requests>=2.32.0
Requires-Dist: beautifulsoup4>=4.13.5
Requires-Dist: google-generativeai>=0.6.0
Requires-Dist: numpy>=1.24.0
Requires-Dist: pandas>=2.1.3
Requires-Dist: scikit-learn>=1.3.2
Requires-Dist: scipy>=1.11.4
Requires-Dist: Pillow>=10.1.0
Requires-Dist: lxml>=4.9.3
Requires-Dist: Werkzeug>=2.3.7
Requires-Dist: typing-extensions>=4.8.0
Requires-Dist: pydantic>=2.5.0
Provides-Extra: dev
Requires-Dist: pytest>=7.0; extra == "dev"
Requires-Dist: pytest-cov>=4.0; extra == "dev"
Requires-Dist: black>=23.0; extra == "dev"
Requires-Dist: flake8>=6.0; extra == "dev"
Dynamic: author
Dynamic: home-page
Dynamic: requires-python
